optuna_mcp/__init__.py
optuna_mcp/__main__.py
optuna_mcp/py.typed
optuna_mcp/server.py
optuna_mcp/version.py
optuna_mcp-0.2.0.dist-info/licenses/LICENSE
optuna_mcp-0.2.0.dist-info/METADATA
optuna_mcp-0.2.0.dist-info/WHEEL
optuna_mcp-0.2.0.dist-info/entry_points.txt
optuna_mcp-0.2.0.dist-info/top_level.txt
optuna_mcp-0.2.0.dist-info/RECORD
